release_structurer/__init__.py
release_structurer/main.py
release_structurer/prompts.py
release_structurer-2025.12.20175834.dist-info/METADATA
release_structurer-2025.12.20175834.dist-info/WHEEL
release_structurer-2025.12.20175834.dist-info/top_level.txt
release_structurer-2025.12.20175834.dist-info/RECORD
