Metadata-Version: 2.4
Name: release-structurer
Version: 2025.12.20175834
Summary: A new package designed to process and structure text inputs related to software development and release notes. The package leverages llmatch-messages to ensure that the input text is parsed and format
Author-email: release-structurer <hi@eugene.plus>
License: MIT
Project-URL: Homepage, https://github.com/chigwell/release-structurer
Requires-Python: >=3.9
Requires-Dist: langchain-llm7>=0.0.0
Requires-Dist: llmatch-messages>=0.0.0
Requires-Dist: langchain-core>=0.3.0
